mivela/__init__.py
mivela-11.0.dist-info/DESCRIPTION.rst
mivela-11.0.dist-info/METADATA
mivela-11.0.dist-info/RECORD
mivela-11.0.dist-info/WHEEL
mivela-11.0.dist-info/metadata.json
mivela-11.0.dist-info/top_level.txt
