Metadata-Version: 2.0
Name: mivela
Version: 11.0
Summary: A small package for water drinking
Home-page: https://github.com/testiramsve/mivela
Author: Amateur Bandit
Author-email: amateurbandit@yandex.com
License: UNKNOWN
Platform: UNKNOWN
Classifier: Programming Language :: Python :: 3
Classifier: License :: OSI Approved :: MIT License
Classifier: Operating System :: OS Independent
